[{
  "id" :35,
  "pv": 9,
  "color": "blue",
  "cost": [6,0,0,0],
  "level": 3,
  "productionCost": [0,2,0,0],
  "product": [0,0,3,0,2]

},{
    "id" :39,
    "pv": 10,
    "color": "blue",
    "cost": [5,0,0,2],
    "level": 3,
    "productionCost": [1,0,1,0],
    "product": [0,2,0,2,1]

},{
    "id" :43,
    "pv": 11,
    "color": "blue",
    "cost": [7,0,0,0],
    "level": 3,
    "productionCost": [0,0,0,1],
    "product": [0,0,1,0,3]

},{
    "id" :47,
    "pv": 12,
    "color": "blue",
    "cost": [4,0,0,4],
    "level": 3,
    "productionCost": [0,1,0,0],
    "product": [1,0,3,0,0]

}]